{
  "SMT2D": {
    "time": 300,
    "optimal": false,
    "obj": 202,
    "sol": [[1, 10, 11]]
  },
  "SMT3D": {
    "time": 300,
    "optimal": false,
    "obj": 1246,
    "sol": [
      [3],
      [13, 16, 12, 10, 15, 17, 8, 4, 1, 11, 9, 7],
      [5],
      [2],
      [6],
      [14]
    ]
  },
  "SMT2D_symmetry": {
    "time": 300,
    "optimal": false,
    "obj": 229,
    "sol": [[15, 14, 6]]
  },
  "SMT3D_symmetry": {
    "time": 300,
    "optimal": false,
    "obj": 1257,
    "sol": [
      [2],
      [3],
      [4, 6],
      [5, 12, 8, 10, 9, 7, 16, 15, 11, 1],
      [13, 17],
      [14]
    ]
  }
}
